memberaudit_securegroups/__init__.py
memberaudit_securegroups/admin.py
memberaudit_securegroups/apps.py
memberaudit_securegroups/auth_hooks.py
memberaudit_securegroups/models.py
memberaudit_securegroups/locale/django.pot
memberaudit_securegroups/locale/cs/LC_MESSAGES/django.mo
memberaudit_securegroups/locale/cs/LC_MESSAGES/django.po
memberaudit_securegroups/locale/de/LC_MESSAGES/django.mo
memberaudit_securegroups/locale/de/LC_MESSAGES/django.po
memberaudit_securegroups/locale/es/LC_MESSAGES/django.mo
memberaudit_securegroups/locale/es/LC_MESSAGES/django.po
memberaudit_securegroups/locale/fr_FR/LC_MESSAGES/django.mo
memberaudit_securegroups/locale/fr_FR/LC_MESSAGES/django.po
memberaudit_securegroups/locale/it_IT/LC_MESSAGES/django.mo
memberaudit_securegroups/locale/it_IT/LC_MESSAGES/django.po
memberaudit_securegroups/locale/ja/LC_MESSAGES/django.mo
memberaudit_securegroups/locale/ja/LC_MESSAGES/django.po
memberaudit_securegroups/locale/ko_KR/LC_MESSAGES/django.mo
memberaudit_securegroups/locale/ko_KR/LC_MESSAGES/django.po
memberaudit_securegroups/locale/nl/LC_MESSAGES/django.mo
memberaudit_securegroups/locale/nl/LC_MESSAGES/django.po
memberaudit_securegroups/locale/pl_PL/LC_MESSAGES/django.mo
memberaudit_securegroups/locale/pl_PL/LC_MESSAGES/django.po
memberaudit_securegroups/locale/ru/LC_MESSAGES/django.mo
memberaudit_securegroups/locale/ru/LC_MESSAGES/django.po
memberaudit_securegroups/locale/sk/LC_MESSAGES/django.mo
memberaudit_securegroups/locale/sk/LC_MESSAGES/django.po
memberaudit_securegroups/locale/uk/LC_MESSAGES/django.mo
memberaudit_securegroups/locale/uk/LC_MESSAGES/django.po
memberaudit_securegroups/locale/zh_Hans/LC_MESSAGES/django.mo
memberaudit_securegroups/locale/zh_Hans/LC_MESSAGES/django.po
memberaudit_securegroups/migrations/0001_initial.py
memberaudit_securegroups/migrations/0002_alter_skillpointfilter_skill_point_threshold_and_more.py
memberaudit_securegroups/migrations/0003_add_corporation_role_filter_and_more.py
aa_memberaudit_securegroups-1.0.1.dist-info/METADATA
aa_memberaudit_securegroups-1.0.1.dist-info/WHEEL
aa_memberaudit_securegroups-1.0.1.dist-info/licenses/LICENSE
aa_memberaudit_securegroups-1.0.1.dist-info/RECORD
