Metadata-Version: 2.3
Name: aa-memberaudit-securegroups
Version: 1.0.1
Summary: Member Audit Secure Groups integration for Alliance Auth.
Project-URL: Changelog, https://gitlab.com/eclipse-expeditions/aa-memberaudit-securegroups/-/blob/master/CHANGELOG.md
Project-URL: Documentation, https://gitlab.com/eclipse-expeditions/aa-memberaudit-securegroups/-/blob/master/README.md
Project-URL: Homepage, https://gitlab.com/eclipse-expeditions/aa-memberaudit-securegroups/
Project-URL: Source, https://gitlab.com/eclipse-expeditions/aa-memberaudit-securegroups.git
Project-URL: Tracker, https://gitlab.com/eclipse-expeditions/aa-memberaudit-securegroups/-/issues
Author-email: Erik Kalkoken <kalkoken87@gmail.com>, Peter Pfeufer <develop@ppfeufer.de>, Rebecca Murphy <rebecca@rcmurphy.me>
Maintainer-email: Peter Pfeufer <develop@ppfeufer.de>
License:                     GNU GENERAL PUBLIC LICENSE
License-File: LICENSE
Keywords: allianceauth,memberaudit,securegroups
Classifier: Environment :: Web Environment
Classifier: Framework :: Django
Classifier: Framework :: Django :: 4.0
Classifier: Framework :: Django :: 4.2
Classifier: Intended Audience :: Developers
Classifier: License :: OSI Approved :: GNU General Public License v3 (GPLv3)
Classifier: Operating System :: OS Independent
Classifier: Programming Language :: Python
Classifier: Programming Language :: Python :: 3 :: Only
Classifier: Programming Language :: Python :: 3.8
Classifier: Programming Language :: Python :: 3.9
Classifier: Programming Language :: Python :: 3.10
Classifier: Programming Language :: Python :: 3.11
Classifier: Programming Language :: Python :: Implementation :: CPython
Classifier: Topic :: Internet :: WWW/HTTP
Classifier: Topic :: Internet :: WWW/HTTP :: Dynamic Content
Requires-Python: ~=3.8
Requires-Dist: aa-memberaudit>=3.3.1
Requires-Dist: allianceauth-securegroups>=0.5.1
Requires-Dist: allianceauth>=3
